LICENSE.txt
MANIFEST.in
README.rst
pyproject.toml
src/sdh.ajax.egg-info/PKG-INFO
src/sdh.ajax.egg-info/SOURCES.txt
src/sdh.ajax.egg-info/dependency_links.txt
src/sdh.ajax.egg-info/requires.txt
src/sdh.ajax.egg-info/top_level.txt
src/sdh/ajax/__init__.py
src/sdh/ajax/accept_ajax.py
src/sdh/ajax/static/js/sdh-ajax.js