Metadata-Version: 2.1
Name: sdh.ajax
Version: 1.0.15
Summary: Utils to store data into json
Author-email: Software Development Hub LLC <dev-tools@sdh.com.ua>, Viacheslav Vic Bukhantsov <vic.bukhantsov@gmail.com>
Maintainer-email: Viacheslav Vic Bukhantsov <vic.bukhantsov@gmail.com>
License: Copyright 2024 Sofrware Development Hub
Project-URL: Homepage, https://bitbucket.org/sdh-llc/sdh-ajax/
Project-URL: Documentation, https://bitbucket.org/sdh-llc/sdh-ajax/
Project-URL: Repository, https://bitbucket.org/sdh-llc/sdh-ajax/
Project-URL: Changelog, https://bitbucket.org/sdh-llc/sdh-ajax/src/master/CHANGELOG.txt
Keywords: ajax,django
Classifier: Development Status :: 5 - Production/Stable
Classifier: Environment :: Web Environment
Classifier: Framework :: Django
Classifier: Intended Audience :: Developers
Classifier: License :: OSI Approved :: BSD License
Classifier: Operating System :: OS Independent
Classifier: Programming Language :: Python
Classifier: Programming Language :: Python :: 3
Classifier: Programming Language :: Python :: 3.6
Classifier: Programming Language :: Python :: 3.7
Classifier: Programming Language :: Python :: 3.8
Classifier: Programming Language :: Python :: 3.10
Classifier: Topic :: Internet :: WWW/HTTP
Classifier: Topic :: Internet :: WWW/HTTP :: Dynamic Content
Classifier: Topic :: Software Development
Classifier: Topic :: Software Development :: Libraries
Requires-Python: >=3.8
License-File: LICENSE.txt
Requires-Dist: Django>=2.2
